setup.py
locaweb_gateway/__init__.py
locaweb_gateway/gateway_http.py
locaweb_gateway/gateway_transaction.py
locaweb_gateway/locaweb_gateway.py
locaweb_gateway.egg-info/PKG-INFO
locaweb_gateway.egg-info/SOURCES.txt
locaweb_gateway.egg-info/dependency_links.txt
locaweb_gateway.egg-info/requires.txt
locaweb_gateway.egg-info/top_level.txt