Metadata-Version: 1.0
Name: locaweb-gateway
Version: v0.1.1
Summary: Locaweb gateway bindings
Home-page: https://github.com/locaweb/locaweb-gateway-python
Author: locaweb
Author-email: saas-dev@locaweb.com.br
License: MIT license
Keywords: locaweb gateway pagamento checkout
Platform: UNKNOWN
